{
  "nome": "Sobrecoxaaotucupi",
  "categoria": "proteína animal",
  "ingredientes": [
    "Sobrecoxa de frango",
    "Tucupi",
    "Tomate cereja",
    "Salsinha picada",
    "Cebolinha picada",
    "Batatas"
  ],
  "descricao": "A sobrecoxa de frango é cozida no tucupi, um caldo extraído da mandioca brava, conferindo um sabor exótico e característico da culinária amazônica. O prato é finalizado com tomate cereja, salsinha e cebolinha picadas para adicionar frescor e cor. As batatas cozidas complementam o prato, oferecendo carboidratos.",
  "beneficios": [
    "O tucupi é rico em carboidratos e nutrientes.",
    "A sobrecoxa de frango é fonte de proteína, essencial para a construção e reparo dos tecidos do corpo.",
    "Os tomates cereja são ricos em licopeno, um antioxidante que protege as células contra danos."
  ],
  "riscos": [
    "O tucupi pode conter ácido cianídrico, que é tóxico, mas o processo de preparo costuma eliminar essa substância.",
    "Alérgenos: não se aplica"
  ],
  "curiosidade": "O tucupi é um ingrediente essencial na culinária do Norte do Brasil, utilizado em diversos pratos típicos como o pato no tucupi.",
  "slug": "sobrecoxaaotucupi",
  "nutricao": {
    "calorias": "",
    "proteinas": "",
    "carboidratos": "",
    "gorduras": ""
  }
}