{
  "slug": "cebolascaramelizadas",
  "nome": "Cebola Caramelizada",
  "categoria": "vegano",
  "descricao": "As cebolas pérola são cozidas em azeite de oliva até caramelizarem, ganhando uma cor dourada e sabor adocicado. Tomates picados e ervas frescas adicionam sabor e aroma. O processo de caramelização envolve a reação de Maillard entre os açúcares naturais da cebola e o calor, resultando em um sabor complexo e agradável.",
  "ingredientes": [
    "Cebolas pérola",
    "Azeite de oliva",
    "Açúcar",
    "Vinagre balsâmico",
    "Salsa picada",
    "Sal",
    "Cebolas pérola (cebolas pequenas)",
    "Tomate picado",
    "Ervas frescas picadas (salsa)",
    "Açúcar (para caramelizar)"
  ],
  "beneficios": [
    "Cebolas são ricas em antioxidantes e compostos sulfurados que auxiliam na saúde cardiovascular.",
    "O processo de caramelização aumenta a disponibilidade de antioxidantes nas cebolas.",
    "Cebolas são ricas em antioxidantes e compostos sulfurados que beneficiam a saúde cardiovascular.",
    "O consumo de cebola pode auxiliar na redução do colesterol LDL."
  ],
  "riscos": [
    "Alto teor de açúcar, se consumido em excesso.",
    "Pessoas com sensibilidade ou alergia a cebola devem evitar o prato.",
    "A caramelização pode aumentar a quantidade de açúcar no prato."
  ],
  "nutricao": {},
  "contem_gluten": false,
  "contem_lactose": false,
  "contem_ovo": false,
  "contem_castanhas": false,
  "contem_frutos_mar": false,
  "contem_soja": false
}