{
  "slug": "quiaboempanado",
  "nome": "Quiabo Empanado",
  "categoria": "proteína animal",
  "descricao": "Quiabo orgânico empanado artesanalmente, assado em forno combinado (sem fritura)",
  "ingredientes": [
    "quiabo orgânico",
    "farinha (uso controlado)",
    "ovo",
    "sal"
  ],
  "tecnica": "Empanado e assado em forno combinado (SEM FRITURA)",
  "beneficios": [
    "Fibras solúveis: regulam colesterol",
    "Vitamina C: fortalece imunidade",
    "Assado: muito mais leve"
  ],
  "riscos": [
    "Contém glúten",
    "Alérgeno: ovo"
  ],
  "contem_gluten": true,
  "nutricao": {
    "calorias": "50 kcal",
    "proteinas": "2g",
    "carboidratos": "10g",
    "gorduras": "0.5g"
  },
  "aviso_cibi_sana": "Sem aditivos químicos e/ou alimentos industrializados/processados",
  "ativo": true,
  "origem": "cibi_sana",
  "created_at": "2026-01-21T15:13:08.326000",
  "updated_at": "2026-01-21T15:13:08.326000",
  "alerta_saude": null,
  "beneficio_principal": "A \"baba\" do quiabo é mucilagem - fibra solúvel que reduz colesterol e controla açúcar no sangue de forma potente",
  "curiosidade_cientifica": "Estudos indianos: extrato de quiabo reduziu glicemia em diabéticos comparável a medicamentos",
  "referencia_pesquisa": "Journal of Pharmacy and Bioallied Sciences, 2020"
}