{
  "nome": "Fígado Acebolado",
  "slug": "fígado_abolado",
  "categoria": "vegano",
  "category_emoji": "🌱",
  "descricao": "Prato com carne e legumes, difícil de identificar com precisão.",
  "ingredientes": [
    "Carne",
    "Legumes",
    "Tomate"
  ],
  "beneficios": [
    "Fonte de ferro",
    "Rico em proteínas",
    "Fonte de vitaminas do complexo B"
  ],
  "riscos": [
    "Alto teor de colesterol (se consumido em excesso)",
    "Alto teor de purinas"
  ],
  "tecnica": "",
  "nutricao": {
    "calorias": "~200 kcal",
    "proteinas": "~10g",
    "carboidratos": "~25g",
    "gorduras": "~8g"
  },
  "contem_gluten": false,
  "contem_lactose": false,
  "contem_ovo": false,
  "contem_castanhas": false,
  "contem_frutos_mar": false,
  "contem_soja": false
}