{
  "nome": "Lasanha De Berinjela",
  "categoria": "vegano",
  "ingredientes": [
    "berinjela",
    "azeite",
    "alho",
    "sal"
  ],
  "descricao": "Berinjela preparada de forma saudável.",
  "beneficios": [
    "Baixas calorias",
    "Rica em fibras",
    "Antioxidantes"
  ],
  "riscos": [],
  "curiosidade": "A berinjela é um vegetal versátil, pertencente à família das solanáceas, assim como o tomate e a batata.",
  "slug": "lasanha_de_berinjela",
  "nutricao": {
    "calorias": "25 kcal",
    "proteinas": "1g",
    "carboidratos": "6g",
    "gorduras": "0.2g"
  },
  "tecnica": "Grelhada ou assada",
  "contem_gluten": false,
  "contem_lactose": false,
  "contem_ovo": false,
  "indice_glicemico": "baixo",
  "tempo_digestao": "2 horas",
  "melhor_horario": "Almoço ou jantar",
  "combina_com": [
    "Queijo",
    "Tomate"
  ],
  "evitar_com": [],
  "category_emoji": "🌱"
}