{
  "nome": "Moqueca de Banana da Terra com Cogumelos",
  "categoria": "vegano",
  "ingredientes": [
    "cogumelos",
    "azeite",
    "alho",
    "sal"
  ],
  "descricao": "Cogumelos saborosos e nutritivos.",
  "beneficios": [
    "Baixas calorias",
    "Proteína vegetal",
    "Rico em vitamina D"
  ],
  "riscos": [],
  "curiosidade": "A moqueca é um prato de origem africana e indígena, muito popular no Brasil, com variações regionais. A banana da terra é uma fruta que, quando cozida, adquire um sabor adocicado e uma textura macia, tornando-a um substituto interessante em diversos pratos.",
  "slug": "moquecadebanadaterra",
  "nutricao": {
    "calorias": "22 kcal",
    "proteinas": "3g",
    "carboidratos": "3g",
    "gorduras": "0.3g"
  },
  "category_emoji": "🌱",
  "contem_gluten": false,
  "contem_lactose": false,
  "contem_ovo": false,
  "contem_castanhas": false,
  "contem_frutos_mar": false,
  "contem_soja": false,
  "tecnica": "Refogado ou grelhado",
  "indice_glicemico": "muito baixo",
  "tempo_digestao": "2 horas",
  "melhor_horario": "Almoço ou jantar",
  "combina_com": [
    "Risotos",
    "Massas"
  ],
  "evitar_com": []
}