{
  "nome": "Goiabada",
  "categoria": "vegano",
  "ingredientes": [
    "Goiaba",
    "Açúcar"
  ],
  "descricao": "A goiabada é uma conserva feita a partir da goiaba, cozida com açúcar até atingir uma consistência espessa e firme. O preparo envolve a remoção de sementes e o cozimento lento da fruta com açúcar, resultando em uma geleia doce e saborosa.",
  "beneficios": [
    "Fonte de energia devido ao alto teor de açúcar.",
    "Contém fibras que auxiliam na digestão (especialmente se for feita com a fruta com casca)."
  ],
  "riscos": [
    "Alto teor de açúcar, portanto, deve ser consumida com moderação. Pode causar picos de glicose no sangue.",
    "Risco de cáries devido ao alto teor de açúcar."
  ],
  "curiosidade": "A goiabada é um doce tradicional no Brasil, frequentemente consumida com queijo coalho ou queijo minas, formando a famosa combinação 'Romeu e Julieta'.",
  "slug": "goiabada",
  "nutricao": {
    "calorias": "",
    "proteinas": "",
    "carboidratos": "",
    "gorduras": ""
  },
  "category_emoji": "🌱",
  "contem_gluten": false,
  "contem_lactose": false,
  "contem_ovo": false,
  "contem_castanhas": false,
  "contem_frutos_mar": false,
  "contem_soja": false
}