{
  "nome": "Carne Seca Com Abóbora",
  "categoria": "proteína animal",
  "ingredientes": [
    "Carne seca desfiada",
    "Abóbora em cubos",
    "Tomate cereja",
    "Cebolinha picada",
    "Ervas frescas (salsa/salsinha)"
  ],
  "descricao": "Prato que apresenta carne seca desfiada, aparentemente refogada, misturada com pedaços de abóbora cozidos e finalizado com tomate cereja e cebolinha fresca picada. A carne seca pode ter sido refogada com temperos e a abóbora parece estar cozida até ficar macia.",
  "beneficios": [
    "A carne seca é rica em proteínas, importantes para a construção e reparação dos tecidos do corpo.",
    "A abóbora é fonte de fibras, que auxiliam na digestão e promovem a saciedade.",
    "Tomate cereja e cebolinha, ricos em vitaminas e antioxidantes."
  ],
  "riscos": [
    "Alto teor de sódio na carne seca (é preciso ter moderação).",
    "O prato pode conter alto teor de gordura, dependendo do método de preparo.",
    "Possível presença de glúten, dependendo dos temperos utilizados."
  ],
  "curiosidade": "A carne seca, também conhecida como charque, é um método de conservação da carne muito utilizado no Brasil, especialmente nas regiões do nordeste.",
  "slug": "carne_seca_com_abóbora",
  "nutricao": {
    "calorias": "",
    "proteinas": "",
    "carboidratos": "",
    "gorduras": ""
  }
}