{
  "nome": "Lasanha De Espinafre",
  "categoria": "vegetariano",
  "ingredientes": [
    "Massa de lasanha",
    "Espinafre",
    "Cogumelo Portobelo",
    "Molho branco (possivelmente à base de leite e amido)",
    "Queijo gratinado (possivelmente mussarela ou queijo parmesão)",
    "Temperos (ervas, alho, cebola)"
  ],
  "descricao": "Lasanha feita com camadas de massa, recheio de espinafre refogado e cogumelos Portobello, coberta com molho branco e gratinada com queijo. O preparo envolve o cozimento da massa, refogar o espinafre e os cogumelos, montar as camadas e assar no forno até gratinar o queijo.",
  "beneficios": [
    "Espinafre rico em ferro, vitaminas e antioxidantes.",
    "Cogumelos Portobello contêm nutrientes e podem auxiliar na saúde do sistema imunológico.",
    "O espinafre auxilia na saúde ocular e óssea."
  ],
  "riscos": [
    "Contém glúten (na massa da lasanha)",
    "Pode conter lactose (no molho branco e queijo)",
    "Alto teor de sódio (dependendo dos temperos e queijos utilizados)"
  ],
  "curiosidade": "O cogumelo Portobello é um cogumelo marrom grande, parente do champignon, e muito utilizado em substituição à carne por sua textura e sabor.",
  "slug": "lasanha_de_espinafre",
  "nutricao": {
    "calorias": "",
    "proteinas": "",
    "carboidratos": "",
    "gorduras": ""
  }
}