{
  "nome": "Espetinho Caprese",
  "categoria": "vegano",
  "ingredientes": [
    "Tomate cereja",
    "Mussarela de búfala",
    "Folhas de manjericão fresco",
    "Azeite de oliva",
    "Palitos de dente"
  ],
  "descricao": "Mini espetinhos com tomate cereja, mussarela de búfala e manjericão fresco, temperados com azeite de oliva.",
  "beneficios": [
    "Fonte de antioxidantes",
    "Rico em cálcio",
    "Fornece vitaminas e minerais"
  ],
  "riscos": [
    "Contém lactose (mussarela)",
    "Alto teor de gordura (azeite e queijo)"
  ],
  "curiosidade": "O nome 'Caprese' vem da ilha de Capri, Itália, onde a salada caprese tradicional teria se originado.",
  "slug": "caprese",
  "nutricao": {
    "calorias": "280 kcal",
    "proteinas": "15g",
    "carboidratos": "5g",
    "gorduras": "20g"
  },
  "category_emoji": "🌱",
  "contem_gluten": false,
  "contem_lactose": true
}